main.py
download_sort-0.1.0.dist-info/METADATA
download_sort-0.1.0.dist-info/WHEEL
download_sort-0.1.0.dist-info/top_level.txt
download_sort-0.1.0.dist-info/RECORD
