Metadata-Version: 2.4
Name: download-sort
Version: 0.1.0
Summary: Add your description here
Requires-Python: >=3.14
Requires-Dist: watchdog>=6.0.0
